lsbatch/__init__.py
lsbatch/__main__.py
lsbatch/batch_job_operations.py
lsbatch/constants.py
lsbatch/gitignore.txt
lsbatch/helper.py
lsbatch/log.py
lsbatch/requests_handler.py
lsbatch/virtual-env-requirements.txt
lsbatch/lsq_batch_template/MXException.py
lsbatch/lsq_batch_template/README.md
lsbatch/lsq_batch_template/__init__.py
lsbatch/lsq_batch_template/batch_details.json
lsbatch/lsq_batch_template/event.json
lsbatch/lsq_batch_template/helper.py
lsbatch/lsq_batch_template/log.py
lsbatch/lsq_batch_template/query.json
lsbatch/lsq_batch_template/sample_query_result.csv
lsbatch/lsq_batch_template/settings.json
lsbatch/lsq_batch_template/startup.py
lsbatch/lsq_batch_template/src/__init__.py
lsbatch/lsq_batch_template/src/main.py
lsbatch-1.1.3.dist-info/LICENSE
lsbatch-1.1.3.dist-info/METADATA
lsbatch-1.1.3.dist-info/WHEEL
lsbatch-1.1.3.dist-info/entry_points.txt
lsbatch-1.1.3.dist-info/top_level.txt
lsbatch-1.1.3.dist-info/RECORD
