Metadata-Version: 2.1
Name: lsbatch
Version: 1.1.3
Summary: lsbatch LeadSquared provided Batch Jobs software development kit. This allows developers to code and test Batch Jobs offline.
Home-page: UNKNOWN
Author: MarketXpander Services Pvt. Ltd.
Author-email: batchjobs@leadsquared.com
License: UNKNOWN
Platform: UNKNOWN
Classifier: Programming Language :: Python :: 3
Classifier: License :: OSI Approved :: MIT License
Classifier: Operating System :: OS Independent
Requires-Python: >=3.6
License-File: LICENSE
